ensemble_eeg/__init__.py
ensemble_eeg/__main__.py
ensemble_eeg/brm_to_edf.py
ensemble_eeg/ensemble_edf.py
ensemble_eeg-0.2.0.dist-info/licenses/LICENSE
ensemble_eeg-0.2.0.dist-info/licenses/NOTICE
ensemble_eeg-0.2.0.dist-info/METADATA
ensemble_eeg-0.2.0.dist-info/WHEEL
ensemble_eeg-0.2.0.dist-info/entry_points.txt
ensemble_eeg-0.2.0.dist-info/top_level.txt
ensemble_eeg-0.2.0.dist-info/RECORD
