Metadata-Version: 2.4
Name: ensemble_eeg
Version: 0.2.0
Summary: Package used to analyze preprocess EDF files for the ENSEMBLE study
Author: Bauke van der Velde
Maintainer: Aymeric Gaudin, Dimitri Papadopoulos Orfanos
Project-URL: Repository, https://github.com/ensemble2/ensemble_eeg
Classifier: Programming Language :: Python
Classifier: Operating System :: OS Independent
Requires-Python: >=3.10
License-File: LICENSE
License-File: NOTICE
Requires-Dist: fire
Requires-Dist: numpy
Requires-Dist: defusedxml
Requires-Dist: dateparser
Dynamic: license-file
